MANIFEST.in
authors.txt
license.txt
setup.cfg
setup.py
redis_queue/__init__.py
redis_queue.egg-info/PKG-INFO
redis_queue.egg-info/SOURCES.txt
redis_queue.egg-info/dependency_links.txt
redis_queue.egg-info/requires.txt
redis_queue.egg-info/top_level.txt
redis_queue.egg-info/zip-safe
redis_queue/tests/__init__.py
redis_queue/tests/test_functional.py