Metadata-Version: 1.0
Name: redis-queue
Version: 0.3
Summary: A persistent, (mostly) atomic queue (like deque or Queue) implemented with redis backing.
Home-page: http://bitbucket.org/npilon/redis_queue/
Author: Nicholas Pilon
Author-email: npilon@oreilly.com
License: Apache
Keywords: queue redis
Platform: UNKNOWN
Classifier: Development Status :: 4 - Beta
Classifier: Intended Audience :: Developers
Classifier: License :: OSI Approved :: Apache Software License
Classifier: Operating System :: OS Independent
Classifier: Programming Language :: Python
Classifier: Topic :: Software Development :: Libraries :: Python Modules
Classifier: Topic :: Database
